ipython_sparql_pandas/__init__.py
ipython_sparql_pandas/sparql.py
ipython_sparql_pandas-1.6.dist-info/LICENSE
ipython_sparql_pandas-1.6.dist-info/METADATA
ipython_sparql_pandas-1.6.dist-info/WHEEL
ipython_sparql_pandas-1.6.dist-info/top_level.txt
ipython_sparql_pandas-1.6.dist-info/RECORD
