Metadata-Version: 2.1
Name: ipython-sparql-pandas
Version: 1.6
Summary: Jupyter/IPython Extension for Sparql Pandas dataframe queries
Home-page: https://github.com/bennokr/ipython_sparql_pandas
Author: Benno Kruit
Author-email: b.b.kruit@vu.nl
License: MIT
Project-URL: Bug Tracker, https://github.com/bennokr/ipython_sparql_pandas/issues
Keywords: sparql,ipython,jupyter extension,magics,ipython,pandas
Classifier: Programming Language :: Python :: 3
Classifier: License :: OSI Approved :: MIT License
Classifier: Operating System :: OS Independent
Requires-Python: >=3.6
License-File: LICENSE
Requires-Dist: ipython
Requires-Dist: SPARQLWrapper
Requires-Dist: pandas
